pepper_lab/__init__.py
pepper_lab/bayesian.py
pepper_lab/datastructure.py
pepper_lab/datastructuresediment.py
pepper_lab/datastructuresludge.py
pepper_lab/datastructuresoil.py
pepper_lab/datastructurewwtp.py
pepper_lab/descriptors.py
pepper_lab/metadata.py
pepper_lab/model.py
pepper_lab/modeling.py
pepper_lab/pepper.py
pepper_lab/predict.py
pepper_lab/util.py
pepper_lab/visualize.py
pepper_lab/wwtp_names.py
pepper_lab-1.1.0.dist-info/LICENSE
pepper_lab-1.1.0.dist-info/METADATA
pepper_lab-1.1.0.dist-info/WHEEL
pepper_lab-1.1.0.dist-info/RECORD
