Metadata-Version: 2.3
Name: pepper-lab
Version: 1.1.0
Summary: PEPPER is a package developed by the Fenner Labs for analyzing and modeling persistence of micropollutants in different environments.
License: MIT License
Author: Jose Cordero
Author-email: jose.cordero@eawag.ch
Requires-Python: >=3.11
Classifier: License :: Other/Proprietary License
Classifier: Programming Language :: Python :: 3
Classifier: Programming Language :: Python :: 3.11
Classifier: Programming Language :: Python :: 3.12
Classifier: Programming Language :: Python :: 3.13
Requires-Dist: emcee (>=3.1.6,<4.0.0)
Requires-Dist: envipath-python (>=0.2.3,<0.3.0)
Requires-Dist: matplotlib (>=3.9.4,<4.0.0)
Requires-Dist: mlxtend (>=0.23.4,<0.24.0)
Requires-Dist: mordredcommunity (>=2.0.6,<3.0.0)
Requires-Dist: numpy (>=2.2.3,<3.0.0)
Requires-Dist: padelpy (>=0.1.14,<0.2.0)
Requires-Dist: pandas (>=2.2.0,<3.0.0)
Requires-Dist: pubchempy (>=1.0.4,<2.0.0)
Requires-Dist: pyyaml (>=6.0.2,<7.0.0)
Requires-Dist: rdkit (>=2024.9.5,<2025.0.0)
Requires-Dist: scikit-learn (>=1.6.1,<2.0.0)
Requires-Dist: seaborn (>=0.13.2,<0.14.0)
Requires-Dist: sklearn-genetic (>=0.6.0,<0.7.0)
Requires-Dist: tqdm (>=4.67.1,<5.0.0)
Requires-Dist: umap (>=0.1.1,<0.2.0)
Project-URL: Repository, https://github.com/FennerLabs/pepper.git
